{"id": 413, "name": "Wave Championship at PGS League NIght -Dec. 7th, 2018 -March 6th, 2019 (Old Points)", "location": "The Portland Game Store", "state": "Oregon", "country": "US", "date": "2019-03-06", "format_id": 1, "version_id": null, "tournament_type_id": 1, "created_at": "2019-03-07T06:57:54.408Z", "updated_at": "2019-03-07T06:57:54.408Z", "participants": [{"id": 7374, "name": "Jared Moderie", "tournament_id": 413, "score": 0, "swiss_rank": 14, "top_cut_rank": null, "mov": 103, "sos": "0.5", "dropped": null, "list_points": null, "list_json": null}, {"id": 7373, "name": "MiloBeall", "tournament_id": 413, "score": 0, "swiss_rank": 13, "top_cut_rank": null, "mov": 148, "sos": "0.75", "dropped": null, "list_points": null, "list_json": null}, {"id": 7372, "name": "David Doncheck", "tournament_id": 413, "score": 0, "swiss_rank": 12, "top_cut_rank": null, "mov": 310, "sos": "0.75", "dropped": null, "list_points": null, "list_json": null}, {"id": 7371, "name": "John Witherspoon ", "tournament_id": 413, "score": 1, "swiss_rank": 11, "top_cut_rank": null, "mov": 394, "sos": "0.63", "dropped": null, "list_points": null, "list_json": null}, {"id": 7370, "name": "Hans Albing", "tournament_id": 413, "score": 1, "swiss_rank": 10, "top_cut_rank": null, "mov": 397, "sos": "0.25", "dropped": null, "list_points": null, "list_json": null}, {"id": 7369, "name": "Stooberty Stu", "tournament_id": 413, "score": 1, "swiss_rank": 9, "top_cut_rank": null, "mov": 551, "sos": "0.5", "dropped": null, "list_points": null, "list_json": null}, {"id": 7368, "name": "Tim Nakayama (\"Diablo\")", "tournament_id": 413, "score": 1, "swiss_rank": 8, "top_cut_rank": null, "mov": 587, "sos": "0.38", "dropped": null, "list_points": null, "list_json": "{\"description\":\"\",\"faction\":\"scumandvillainy\",\"name\":\"PGS Wave 1 Championships\",\"pilots\":[{\"id\":\"bobafett\",\"name\":\"bobafett\",\"points\":116,\"ship\":\"firesprayclasspatrolcraft\",\"upgrades\":{\"talent\":[\"trickshot\"],\"crew\":[\"perceptivecopilot\"],\"device\":[\"proximitymines\"],\"illicit\":[\"contrabandcybernetics\"],\"title\":[\"slavei\"],\"torpedo\":[\"protontorpedoes\"]}},{\"id\":\"jakkugunrunner\",\"name\":\"jakkugunrunner\",\"points\":28,\"ship\":\"quadrijettransferspacetug\"},{\"id\":\"jakkugunrunner\",\"name\":\"jakkugunrunner\",\"points\":28,\"ship\":\"quadrijettransferspacetug\"},{\"id\":\"jakkugunrunner\",\"name\":\"jakkugunrunner\",\"points\":28,\"ship\":\"quadrijettransferspacetug\"}],\"points\":200,\"vendor\":{\"yasb\":{\"builder\":\"Yet Another Squad Builder 2.0\",\"builder_url\":\"https://raithos.github.io/\",\"link\":\"https://raithos.github.io/?f=Scum%20and%20Villainy&d=v5!s!103:133,-1,-1,54,70,92,-1,161:U.136;143:-1,-1,-1,-1,-1:;143:-1,-1,-1,-1,-1:;143:-1,-1,-1,-1,-1:&sn=PGS%20Wave%201%20Championships&obs=\"}},\"version\":\"2.0.0\"}"}, {"id": 7367, "name": "George Irwin", "tournament_id": 413, "score": 2, "swiss_rank": 7, "top_cut_rank": null, "mov": 780, "sos": "0.56", "dropped": null, "list_points": null, "list_json": null}, {"id": 7366, "name": "Marc Verebely", "tournament_id": 413, "score": 2, "swiss_rank": 6, "top_cut_rank": null, "mov": 797, "sos": "0.5", "dropped": null, "list_points": null, "list_json": null}, {"id": 7365, "name": "Paul Nelson", "tournament_id": 413, "score": 2, "swiss_rank": 5, "top_cut_rank": null, "mov": 955, "sos": "0.31", "dropped": null, "list_points": null, "list_json": "{\"faction\":\"scumandvillainy\",\"pilots\":[{\"id\":\"moraloeval\",\"ship\":\"yv666lightfreighter\",\"upgrades\":{\"crew\":[\"000\",\"lattsrazzi\",\"l337\"],\"ept\":[\"trickshot\"]},\"points\":87},{\"id\":\"guri\",\"ship\":\"starviperclassattackplatform\",\"upgrades\":{\"sensor\":[\"advancedsensors\"],\"modification\":[\"shieldupgrade\"],\"ept\":[\"elusive\"]},\"points\":81},{\"id\":\"sunnybounder\",\"ship\":\"m3ainterceptor\",\"points\":31}],\"name\":\"Time Walk Moralla\",\"description\":\"\",\"points\":199}"}, {"id": 7364, "name": "Jeff Bassett", "tournament_id": 413, "score": 3, "swiss_rank": 4, "top_cut_rank": null, "mov": 883, "sos": "0.5", "dropped": null, "list_points": null, "list_json": "{\"description\":\"\",\"faction\":\"rebelalliance\",\"name\":\"Unnamed Squadron\",\"pilots\":[{\"id\":\"hortonsalm\",\"name\":\"hortonsalm\",\"points\":51,\"ship\":\"btla4ywing\",\"upgrades\":{\"talent\":[\"trickshot\"],\"turret\":[\"dorsalturret\"],\"gunner\":[\"veteranturretgunner\"]}},{\"id\":\"evaanverlaine\",\"name\":\"evaanverlaine\",\"points\":40,\"ship\":\"btla4ywing\",\"upgrades\":{\"turret\":[\"dorsalturret\"]}},{\"id\":\"jakefarrell\",\"name\":\"jakefarrell\",\"points\":40,\"ship\":\"rz1awing\"},{\"id\":\"arvelcrynyd\",\"name\":\"arvelcrynyd\",\"points\":39,\"ship\":\"rz1awing\",\"upgrades\":{\"talent\":[\"intimidation\"]}},{\"id\":\"lieutenantblount\",\"name\":\"lieutenantblount\",\"points\":30,\"ship\":\"z95af4headhunter\"}],\"points\":200,\"vendor\":{\"yasb\":{\"builder\":\"Yet Another Squad Builder 2.0\",\"builder_url\":\"https://raithos.github.io/\",\"link\":\"https://raithos.github.io/?f=Rebel%20Alliance&d=v5!s!26:133,137,-1,-1,-1,-1,90:;28:-1,137,-1,-1,-1,-1,-1:;50:-1,-1:;51:122,-1:;55:-1,-1,-1:&sn=Unnamed%20Squadron&obs=\"}},\"version\":\"2.0.0\"}"}, {"id": 7363, "name": "Josh mattison", "tournament_id": 413, "score": 3, "swiss_rank": 3, "top_cut_rank": null, "mov": 950, "sos": "0.56", "dropped": null, "list_points": null, "list_json": null}, {"id": 7362, "name": "Craig Miller", "tournament_id": 413, "score": 3, "swiss_rank": 2, "top_cut_rank": null, "mov": 1073, "sos": "0.56", "dropped": null, "list_points": null, "list_json": null}, {"id": 7361, "name": "sozin", "tournament_id": 413, "score": 4, "swiss_rank": 1, "top_cut_rank": null, "mov": 1272, "sos": "0.44", "dropped": null, "list_points": null, "list_json": "{\"description\":\"\",\"faction\":\"galacticempire\",\"name\":\"Imperial Shotgun\",\"pilots\":[{\"id\":\"majorrhymer\",\"name\":\"majorrhymer\",\"points\":45,\"ship\":\"tiesabomber\",\"upgrades\":{\"torpedo\":[\"advprotontorpedoes\"],\"missile\":[\"clustermissiles\"]}},{\"id\":\"captainjonus\",\"name\":\"captainjonus\",\"points\":42,\"ship\":\"tiesabomber\",\"upgrades\":{\"missile\":[\"barragerockets\"]}},{\"id\":\"deathrain\",\"name\":\"deathrain\",\"points\":60,\"ship\":\"tiecapunisher\",\"upgrades\":{\"sensor\":[\"trajectorysimulator\"],\"torpedo\":[\"advprotontorpedoes\"],\"missile\":[\"barragerockets\"],\"device\":[\"seismiccharges\"]}},{\"id\":\"redline\",\"name\":\"redline\",\"points\":53,\"ship\":\"tiecapunisher\",\"upgrades\":{\"torpedo\":[\"protontorpedoes\"]}}],\"points\":200,\"vendor\":{\"yasb\":{\"builder\":\"Yet Another Squad Builder 2.0\",\"builder_url\":\"https://raithos.github.io/\",\"link\":\"https://raithos.github.io/?f=Galactic%20Empire&d=v5!s!204:-1,134,98,-1,-1,-1,-1,-1:;203:-1,-1,97,-1,-1,-1,-1,-1:;192:114,134,97,-1,-1,71,-1,-1:;191:-1,136,-1,-1,-1,-1,-1,-1:&sn=Imperial%20Shotgun&obs=\"}},\"version\":\"2.0.0\"}"}], "rounds": [{"id": 11, "tournament_id": 413, "roundtype_id": 1, "round_number": 4, "matches": [{"id": 1046, "player1_id": 7366, "player1_points": 200, "player2_id": 7368, "player2_points": 78, "result": "win", "winner_id": 7366}, {"id": 1045, "player1_id": 7365, "player1_points": 200, "player2_id": 7371, "player2_points": 36, "result": "win", "winner_id": 7365}, {"id": 1044, "player1_id": 7364, "player1_points": 200, "player2_id": 7369, "player2_points": 70, "result": "win", "winner_id": 7364}, {"id": 1043, "player1_id": 7362, "player1_points": 200, "player2_id": 7367, "player2_points": 115, "result": "win", "winner_id": 7362}, {"id": 1042, "player1_id": 7363, "player1_points": 53, "player2_id": 7361, "player2_points": 200, "result": "win", "winner_id": 7361}]}, {"id": 10, "tournament_id": 413, "roundtype_id": 1, "round_number": 3, "matches": [{"id": 1041, "player1_id": 7368, "player1_points": 136, "player2_id": 7369, "player2_points": 200, "result": "win", "winner_id": 7369}, {"id": 1040, "player1_id": 7365, "player1_points": 76, "player2_id": 7364, "player2_points": 114, "result": "win", "winner_id": 7364}, {"id": 1039, "player1_id": 7366, "player1_points": 17, "player2_id": 7362, "player2_points": 200, "result": "win", "winner_id": 7362}, {"id": 1038, "player1_id": 7361, "player1_points": 200, "player2_id": 7371, "player2_points": 21, "result": "win", "winner_id": 7361}, {"id": 1037, "player1_id": 7363, "player1_points": 200, "player2_id": 7367, "player2_points": 100, "result": "win", "winner_id": 7363}]}, {"id": 9, "tournament_id": 413, "roundtype_id": 1, "round_number": 2, "matches": [{"id": 1036, "player1_id": 7366, "player1_points": 200, "player2_id": 7369, "player2_points": 82, "result": "win", "winner_id": 7366}, {"id": 1035, "player1_id": 7372, "player1_points": 127, "player2_id": 7365, "player2_points": 157, "result": "win", "winner_id": 7365}, {"id": 1034, "player1_id": 7368, "player1_points": 78, "player2_id": 7371, "player2_points": 106, "result": "win", "winner_id": 7371}, {"id": 1033, "player1_id": 7363, "player1_points": 200, "player2_id": 7364, "player2_points": 55, "result": "win", "winner_id": 7363}, {"id": 1032, "player1_id": 7367, "player1_points": 200, "player2_id": 7370, "player2_points": 100, "result": "win", "winner_id": 7367}, {"id": 1031, "player1_id": 7362, "player1_points": 80, "player2_id": 7361, "player2_points": 166, "result": "win", "winner_id": 7361}]}, {"id": 8, "tournament_id": 413, "roundtype_id": 1, "round_number": 1, "matches": [{"id": 1030, "player1_id": 7362, "player1_points": 176, "player2_id": 7371, "player2_points": 85, "result": "win", "winner_id": 7362}, {"id": 1029, "player1_id": 7364, "player1_points": 166, "player2_id": 7366, "player2_points": 106, "result": "win", "winner_id": 7364}, {"id": 1028, "player1_id": 7365, "player1_points": 100, "player2_id": 7368, "player2_points": 101, "result": "win", "winner_id": 7368}, {"id": 1027, "player1_id": 7369, "player1_points": 90, "player2_id": 7367, "player2_points": 155, "result": "win", "winner_id": 7367}, {"id": 1026, "player1_id": 7363, "player1_points": 132, "player2_id": 7373, "player2_points": 80, "result": "win", "winner_id": 7363}, {"id": 1025, "player1_id": 7374, "player1_points": 103, "player2_id": 7370, "player2_points": 200, "result": "win", "winner_id": 7370}, {"id": 1024, "player1_id": 7372, "player1_points": 140, "player2_id": 7361, "player2_points": 200, "result": "win", "winner_id": 7361}]}]}