{"id": 423, "name": "Atlanta Sci-fi and Fantasy Expo Hyperspace Wave 2", "location": "Challenges Games and Comics", "state": "Ga", "country": "US", "date": "2019-03-09", "format_id": 34, "version_id": null, "tournament_type_id": 1, "created_at": "2019-03-10T05:26:52.763Z", "updated_at": "2019-03-10T05:26:52.763Z", "participants": [{"id": 7691, "name": null, "tournament_id": 423, "score": null, "swiss_rank": 10, "top_cut_rank": null, "mov": null, "sos": null, "dropped": null, "list_points": null, "list_json": null}, {"id": 7690, "name": null, "tournament_id": 423, "score": null, "swiss_rank": 9, "top_cut_rank": null, "mov": null, "sos": null, "dropped": null, "list_points": null, "list_json": null}, {"id": 7689, "name": null, "tournament_id": 423, "score": null, "swiss_rank": 8, "top_cut_rank": null, "mov": null, "sos": null, "dropped": null, "list_points": null, "list_json": null}, {"id": 7688, "name": null, "tournament_id": 423, "score": null, "swiss_rank": 7, "top_cut_rank": null, "mov": null, "sos": null, "dropped": null, "list_points": null, "list_json": null}, {"id": 7687, "name": null, "tournament_id": 423, "score": null, "swiss_rank": 6, "top_cut_rank": null, "mov": null, "sos": null, "dropped": null, "list_points": null, "list_json": null}, {"id": 7686, "name": null, "tournament_id": 423, "score": null, "swiss_rank": 5, "top_cut_rank": null, "mov": null, "sos": null, "dropped": null, "list_points": null, "list_json": null}, {"id": 7685, "name": null, "tournament_id": 423, "score": null, "swiss_rank": 4, "top_cut_rank": null, "mov": null, "sos": null, "dropped": null, "list_points": null, "list_json": null}, {"id": 7684, "name": null, "tournament_id": 423, "score": null, "swiss_rank": 3, "top_cut_rank": null, "mov": null, "sos": null, "dropped": null, "list_points": null, "list_json": null}, {"id": 7683, "name": null, "tournament_id": 423, "score": null, "swiss_rank": 2, "top_cut_rank": null, "mov": null, "sos": null, "dropped": null, "list_points": null, "list_json": null}, {"id": 7682, "name": null, "tournament_id": 423, "score": null, "swiss_rank": 1, "top_cut_rank": null, "mov": null, "sos": null, "dropped": null, "list_points": null, "list_json": null}], "rounds": []}