{"id": 555, "name": "The DefconHyperSpace", "location": "Defcon 2.0", "state": "Varese", "country": "IT", "date": "2019-04-14", "format_id": 34, "version_id": null, "tournament_type_id": 3, "created_at": "2019-04-16T11:14:41.456Z", "updated_at": "2019-05-17T09:15:54.695Z", "participants": [{"id": 11034, "name": "Pividori Marco", "tournament_id": 555, "score": 4, "swiss_rank": 13, "top_cut_rank": null, "mov": 1478, "sos": "0.5", "dropped": false, "list_points": null, "list_json": "{\"faction\":\"galacticempire\",\"pilots\":[{\"id\":\"darthvader\",\"ship\":\"tieadvancedx1\",\"points\":73,\"upgrades\":{\"sensor\":[\"firecontrolsystem\"],\"modification\":[\"afterburners\"]}},{\"id\":\"soontirfel\",\"ship\":\"tieinterceptor\",\"points\":65,\"upgrades\":{\"talent\":[\"juke\"],\"modification\":[\"shieldupgrade\"]}},{\"id\":\"majorvermeil\",\"ship\":\"tiereaper\",\"points\":49}],\"points\":187,\"vendor\":{\"yasb\":{\"builder\":\"(Yet Another) X-Wing Miniatures Squad Builder\",\"builder_url\":\"https://raithos.github.io\",\"link\":\"https://raithos.github.io/?f=Galactic%20Empire&d=v6!h=200!173:,113,,105:;179:123,165,:;183:,,,:&sn=Baron%20Vader%20Reaper&obs=coreasteroid5,core2asteroid4,core2asteroid5\"}},\"version\":\"2.0.0\",\"name\":\"Baron Vader Reaper\",\"obstacles\":[\"coreasteroid5\",\"core2asteroid4\",\"core2asteroid5\"]}"}, {"id": 11074, "name": "Sorgato Nevio", "tournament_id": 555, "score": 2, "swiss_rank": 53, "top_cut_rank": null, "mov": 1199, "sos": "0.44", "dropped": false, "list_points": null, "list_json": "{\"faction\":\"resistance\",\"pilots\":[{\"id\":\"poedameron\",\"ship\":\"t70xwing\",\"points\":73,\"upgrades\":{\"talent\":[\"heroic\"],\"astromech\":[\"r4astromech\"],\"configuration\":[\"integratedsfoils\"],\"title\":[\"blackone\"],\"cannon\":[\"jammingbeam\"]}},{\"id\":\"niennunb\",\"ship\":\"t70xwing\",\"points\":61,\"upgrades\":{\"talent\":[\"heroic\"],\"configuration\":[\"integratedsfoils\"],\"tech\":[\"patternanalyzer\"],\"cannon\":[\"jammingbeam\"]}},{\"id\":\"elloasty\",\"ship\":\"t70xwing\",\"points\":57,\"upgrades\":{\"talent\":[\"heroic\"],\"configuration\":[\"integratedsfoils\"],\"cannon\":[\"jammingbeam\"]}}],\"points\":191,\"vendor\":{\"yasb\":{\"builder\":\"(Yet Another) X-Wing Miniatures Squad Builder\",\"builder_url\":\"https://raithos.github.io\",\"link\":\"https://raithos.github.io/?f=Resistance&d=v6!s=200!231:172,5,,175,,171,12:;298:172,,,175,206,,12:;299:172,,,175,,,12:&sn=Unnamed%20Squadron&obs=\"}},\"version\":\"2.0.0\"}"}, {"id": 11077, "name": "Scarsi Mattia", "tournament_id": 555, "score": 2, "swiss_rank": 56, "top_cut_rank": null, "mov": 1081, "sos": "0.42", "dropped": false, "list_points": null, "list_json": "{\"faction\":\"separatistalliance\",\"pilots\":[{\"id\":\"generalgrievous\",\"ship\":\"belbullab22starfighter\",\"upgrades\":{\"modification\":[\"imperviumplating\"],\"title\":[\"soullessone\"],\"tactical-relay\":[\"kraken\"],\"ept\":[\"outmaneuver\"]},\"points\":79},{\"id\":\"dfs311\",\"ship\":\"vultureclassdroidfighter\",\"upgrades\":{\"configuration\":[\"grapplingstruts\"],\"missile\":[\"discordmissiles\"]},\"points\":33},{\"id\":\"tradefederationdrone\",\"ship\":\"vultureclassdroidfighter\",\"upgrades\":{\"configuration\":[\"grapplingstruts\"],\"missile\":[\"discordmissiles\"]},\"points\":29},{\"id\":\"tradefederationdrone\",\"ship\":\"vultureclassdroidfighter\",\"upgrades\":{\"configuration\":[\"grapplingstruts\"],\"missile\":[\"discordmissiles\"]},\"points\":29},{\"id\":\"haorchallprototype\",\"ship\":\"vultureclassdroidfighter\",\"upgrades\":{\"configuration\":[\"grapplingstruts\"],\"missile\":[\"energyshellcharges\"]},\"points\":30}],\"name\":\"Grievous volture\",\"description\":\"\",\"points\":200,\"vendor\":{\"sb2xws\":{\"builder\":\"SB2XWS\",\"url\":\"http://sb2xws.herokuapp.com/translate/14a8c7db-7793-42aa-b704-b90d338f4bb0\"}}}"}, {"id": 11047, "name": "Sapone Alessandro", "tournament_id": 555, "score": 4, "swiss_rank": 26, "top_cut_rank": null, "mov": 1234, "sos": "0.44", "dropped": false, "list_points": null, "list_json": "{\"faction\":\"separatistalliance\",\"pilots\":[{\"id\":\"tradefederationdrone\",\"ship\":\"vultureclassdroidfighter\",\"upgrades\":{\"missile\":[\"energyshellcharges\"]},\"points\":24},{\"id\":\"tradefederationdrone\",\"ship\":\"vultureclassdroidfighter\",\"upgrades\":{\"missile\":[\"energyshellcharges\"]},\"points\":24},{\"id\":\"tradefederationdrone\",\"ship\":\"vultureclassdroidfighter\",\"upgrades\":{\"missile\":[\"energyshellcharges\"]},\"points\":24},{\"id\":\"tradefederationdrone\",\"ship\":\"vultureclassdroidfighter\",\"upgrades\":{\"missile\":[\"energyshellcharges\"]},\"points\":24},{\"id\":\"tradefederationdrone\",\"ship\":\"vultureclassdroidfighter\",\"upgrades\":{\"missile\":[\"energyshellcharges\"]},\"points\":24},{\"id\":\"captainsear\",\"ship\":\"belbullab22starfighter\",\"upgrades\":{\"tactical-relay\":[\"kraken\"]},\"points\":49},{\"id\":\"dfs311\",\"ship\":\"vultureclassdroidfighter\",\"upgrades\":{\"missile\":[\"energyshellcharges\"]},\"points\":28}],\"name\":\"Sear + sciame\",\"description\":\"\",\"points\":197,\"vendor\":{\"sb2xws\":{\"builder\":\"SB2XWS\",\"url\":\"http://sb2xws.herokuapp.com/translate/f67f04d2-62d5-4b90-9ee8-f7a8cc2f1bd1\"}}}"}, {"id": 11053, "name": "Valenza Federico", "tournament_id": 555, "score": 3, "swiss_rank": 32, "top_cut_rank": null, "mov": 1429, "sos": "0.58", "dropped": false, "list_points": null, "list_json": "{\"faction\":\"firstorder\",\"pilots\":[{\"id\":\"kyloren\",\"ship\":\"tievnsilencer\",\"points\":76},{\"id\":\"lieutenanttavson\",\"ship\":\"upsilonclassshuttle\",\"upgrades\":{\"cannon\":[\"jammingbeam\"]},\"points\":62},{\"id\":\"pettyofficerthanisson\",\"ship\":\"upsilonclassshuttle\",\"upgrades\":{\"cannon\":[\"jammingbeam\"]},\"points\":60}],\"name\":\"FEDERICO VALENZA\",\"description\":\"\",\"points\":198,\"vendor\":{\"sb2xws\":{\"builder\":\"SB2XWS\",\"url\":\"http://sb2xws.herokuapp.com/translate/90e60506-511c-490a-b2c5-7e29e27dfad9\"}}}"}, {"id": 11068, "name": "Battaglia Michele", "tournament_id": 555, "score": 3, "swiss_rank": 47, "top_cut_rank": null, "mov": 1042, "sos": "0.56", "dropped": false, "list_points": null, "list_json": "{\"faction\":\"galacticempire\",\"pilots\":[{\"id\":\"darthvader\",\"ship\":\"tieadvancedx1\",\"points\":80,\"upgrades\":{\"force-power\":[\"hate\"],\"sensor\":[\"collisiondetector\"],\"modification\":[\"afterburners\"]}},{\"id\":\"majorvermeil\",\"ship\":\"tiereaper\",\"points\":58,\"upgrades\":{\"talent\":[\"crackshot\"],\"crew\":[\"directorkrennic\"],\"modification\":[\"hullupgrade\"]}},{\"id\":\"seynmarana\",\"ship\":\"tielnfighter\",\"points\":31,\"upgrades\":{\"talent\":[\"marksmanship\"]}},{\"id\":\"gideonhask\",\"ship\":\"tielnfighter\",\"points\":31,\"upgrades\":{\"talent\":[\"crackshot\"]}}],\"points\":200,\"vendor\":{\"yasb\":{\"builder\":\"(Yet Another) X-Wing Miniatures Squad Builder\",\"builder_url\":\"https://raithos.github.io\",\"link\":\"https://raithos.github.io/?f=Galactic%20Empire&d=v6!h=200!173:204,112,,105:;183:116,28,,164:;224:125,:;223:116,:&sn=Unnamed%20Squadron&obs=\"}},\"version\":\"2.0.0\"}"}, {"id": 11071, "name": "Paro Alessandro", "tournament_id": 555, "score": 3, "swiss_rank": 50, "top_cut_rank": null, "mov": 952, "sos": "0.51", "dropped": false, "list_points": null, "list_json": "{\"faction\":\"firstorder\",\"pilots\":[{\"id\":\"zetasquadronsurvivor\",\"ship\":\"tiesffighter\",\"points\":40,\"upgrades\":{\"missile\":[\"clustermissiles\"],\"modification\":[\"munitionsfailsafe\"]}},{\"id\":\"zetasquadronsurvivor\",\"ship\":\"tiesffighter\",\"points\":40,\"upgrades\":{\"missile\":[\"clustermissiles\"],\"modification\":[\"munitionsfailsafe\"]}},{\"id\":\"zetasquadronsurvivor\",\"ship\":\"tiesffighter\",\"points\":40,\"upgrades\":{\"missile\":[\"clustermissiles\"],\"modification\":[\"munitionsfailsafe\"]}},{\"id\":\"zetasquadronsurvivor\",\"ship\":\"tiesffighter\",\"points\":40,\"upgrades\":{\"missile\":[\"clustermissiles\"],\"modification\":[\"munitionsfailsafe\"]}},{\"id\":\"zetasquadronsurvivor\",\"ship\":\"tiesffighter\",\"points\":40,\"upgrades\":{\"missile\":[\"clustermissiles\"],\"modification\":[\"munitionsfailsafe\"]}}],\"points\":200,\"vendor\":{\"yasb\":{\"builder\":\"(Yet Another) X-Wing Miniatures Squad Builder\",\"builder_url\":\"https://raithos.github.io\",\"link\":\"https://raithos.github.io/?f=First%20Order&d=v6!h=200!259:,,98,,108:;259:,,98,,108:;259:,,98,,108:;259:,,98,,108:;259:,,98,,108:&sn=Unnamed%20Squadron&obs=\"}},\"version\":\"2.0.0\"}"}, {"id": 11049, "name": "Gioda Davide", "tournament_id": 555, "score": 3, "swiss_rank": 28, "top_cut_rank": null, "mov": 1484, "sos": "0.33", "dropped": false, "list_points": null, "list_json": "{\"faction\":\"firstorder\",\"pilots\":[{\"id\":\"zetasquadronsurvivor\",\"ship\":\"tiesffighter\",\"points\":40,\"upgrades\":{\"missile\":[\"clustermissiles\"],\"modification\":[\"munitionsfailsafe\"]}},{\"id\":\"zetasquadronsurvivor\",\"ship\":\"tiesffighter\",\"points\":40,\"upgrades\":{\"missile\":[\"clustermissiles\"],\"modification\":[\"munitionsfailsafe\"]}},{\"id\":\"zetasquadronsurvivor\",\"ship\":\"tiesffighter\",\"points\":40,\"upgrades\":{\"missile\":[\"clustermissiles\"],\"modification\":[\"munitionsfailsafe\"]}},{\"id\":\"zetasquadronsurvivor\",\"ship\":\"tiesffighter\",\"points\":40,\"upgrades\":{\"missile\":[\"clustermissiles\"],\"modification\":[\"munitionsfailsafe\"]}},{\"id\":\"zetasquadronsurvivor\",\"ship\":\"tiesffighter\",\"points\":40,\"upgrades\":{\"missile\":[\"clustermissiles\"],\"modification\":[\"munitionsfailsafe\"]}}],\"points\":200,\"vendor\":{\"yasb\":{\"builder\":\"(Yet Another) X-Wing Miniatures Squad Builder\",\"builder_url\":\"https://raithos.github.io\",\"link\":\"https://raithos.github.io/?f=First%20Order&d=v6!h=200!259:,,98,,108:;259:,,98,,108:;259:,,98,,108:;259:,,98,,108:;259:,,98,,108:&sn=Unnamed%20Squadron&obs=\"}},\"version\":\"2.0.0\"}"}, {"id": 11063, "name": "Benciolini Francesco", "tournament_id": 555, "score": 3, "swiss_rank": 42, "top_cut_rank": null, "mov": 1212, "sos": "0.5", "dropped": false, "list_points": null, "list_json": "{\"faction\":\"resistance\",\"pilots\":[{\"id\":\"vennie\",\"ship\":\"mg100starfortress\",\"points\":108,\"upgrades\":{\"sensor\":[\"trajectorysimulator\"],\"tech\":[\"patternanalyzer\"],\"crew\":[\"c3po-crew\"],\"gunner\":[\"veteranturretgunner\",\"rey-gunner\"],\"device\":[\"protonbombs\"]}},{\"id\":\"tallissanlintra\",\"ship\":\"rz2awing\",\"points\":37,\"upgrades\":{\"talent\":[\"crackshot\",\"heroic\"]}},{\"id\":\"lieutenantbastian\",\"ship\":\"t70xwing\",\"points\":55,\"upgrades\":{\"astromech\":[\"m9g8\"],\"configuration\":[\"integratedsfoils\"]}}],\"points\":200,\"vendor\":{\"yasb\":{\"builder\":\"(Yet Another) X-Wing Miniatures Squad Builder\",\"builder_url\":\"https://raithos.github.io\",\"link\":\"https://raithos.github.io/?f=Resistance&d=v6!s=200!294:114,206,191,90,187,69,,:;240:116,172,,:;254:197,,175,,,:&sn=VennieAX&obs=\"}},\"version\":\"2.0.0\",\"name\":\"VennieAX\"}"}, {"id": 11036, "name": "Magi Stefano", "tournament_id": 555, "score": 4, "swiss_rank": 15, "top_cut_rank": null, "mov": 1462, "sos": "0.75", "dropped": false, "list_points": null, "list_json": "{\"faction\":\"galacticempire\",\"pilots\":[{\"id\":\"darthvader\",\"ship\":\"tieadvancedx1\",\"points\":73,\"upgrades\":{\"sensor\":[\"firecontrolsystem\"],\"modification\":[\"afterburners\"]}},{\"id\":\"soontirfel\",\"ship\":\"tieinterceptor\",\"points\":61,\"upgrades\":{\"talent\":[\"predator\"],\"modification\":[\"hullupgrade\"]}},{\"id\":\"duchess\",\"ship\":\"tieskstriker\",\"points\":48,\"upgrades\":{\"modification\":[\"afterburners\"]}}],\"points\":182,\"vendor\":{\"yasb\":{\"builder\":\"(Yet Another) X-Wing Miniatures Squad Builder\",\"builder_url\":\"https://raithos.github.io\",\"link\":\"https://raithos.github.io/?f=Galactic%20Empire&d=v6!s=200!173:,113,,105:;179:127,164,:;211:,,,105:&sn=Unnamed%20Squadron&obs=\"}},\"version\":\"2.0.0\"}"}, {"id": 11066, "name": "Ravizza Daniele", "tournament_id": 555, "score": 3, "swiss_rank": 45, "top_cut_rank": null, "mov": 1142, "sos": "0.44", "dropped": false, "list_points": null, "list_json": "{\"faction\":\"galacticempire\",\"pilots\":[{\"id\":\"soontirfel\",\"ship\":\"tieinterceptor\",\"points\":74,\"upgrades\":{\"talent\":[\"outmaneuver\"],\"modification\":[\"stealthdevice\",\"shieldupgrade\"]}},{\"id\":\"darthvader\",\"ship\":\"tieadvancedx1\",\"points\":76,\"upgrades\":{\"force-power\":[\"hate\"],\"sensor\":[\"firecontrolsystem\"],\"modification\":[\"afterburners\"]}},{\"id\":\"duchess\",\"ship\":\"tieskstriker\",\"points\":49,\"upgrades\":{\"talent\":[\"crackshot\"],\"modification\":[\"shieldupgrade\"]}}],\"points\":199,\"vendor\":{\"yasb\":{\"builder\":\"(Yet Another) X-Wing Miniatures Squad Builder\",\"builder_url\":\"https://raithos.github.io\",\"link\":\"https://raithos.github.io/?f=Galactic%20Empire&d=v6!h=200!179:126,166,165:;173:204,113,,105:;211:116,,,165:&sn=Hypertrial%20Legnano&obs=\"}},\"version\":\"2.0.0\",\"name\":\"Hypertrial Legnano\"}"}, {"id": 11059, "name": "Rossi Stefano", "tournament_id": 555, "score": 3, "swiss_rank": 38, "top_cut_rank": null, "mov": 1267, "sos": "0.56", "dropped": false, "list_points": null, "list_json": "{\"faction\":\"rebelalliance\",\"pilots\":[{\"id\":\"hansolo-modifiedyt1300lightfreighter\",\"ship\":\"modifiedyt1300lightfreighter\",\"points\":95,\"upgrades\":{\"talent\":[\"trickshot\"],\"crew\":[\"leiaorgana\",\"r2d2-crew\"],\"illicit\":[\"inertialdampeners\"]}},{\"id\":\"lukeskywalker\",\"ship\":\"t65xwing\",\"points\":62,\"upgrades\":{\"configuration\":[\"servomotorsfoils\"]}},{\"id\":\"jakefarrell\",\"ship\":\"rz1awing\",\"points\":37,\"upgrades\":{\"talent\":[\"crackshot\"]}}],\"points\":194,\"vendor\":{\"yasb\":{\"builder\":\"(Yet Another) X-Wing Miniatures Squad Builder\",\"builder_url\":\"https://raithos.github.io\",\"link\":\"https://raithos.github.io/?f=Rebel%20Alliance&d=v6!h=200!42:133,,,46,56,,,95:;4:,,,,142:;50:116,,:&sn=Unnamed%20Squadron&obs=\"}},\"version\":\"2.0.0\"}"}, {"id": 11030, "name": "de Scordilli Marco", "tournament_id": 555, "score": 4, "swiss_rank": 9, "top_cut_rank": null, "mov": 1652, "sos": "0.58", "dropped": false, "list_points": null, "list_json": "{\"faction\":\"resistance\",\"pilots\":[{\"id\":\"poedameron\",\"ship\":\"t70xwing\",\"points\":73,\"upgrades\":{\"talent\":[\"heroic\"],\"astromech\":[\"r4astromech\"],\"configuration\":[\"integratedsfoils\"],\"title\":[\"blackone\"],\"hardpoint\":[\"hardpointcannon\"],\"cannon\":[\"jammingbeam\"]}},{\"id\":\"lulolampar\",\"ship\":\"rz2awing\",\"points\":40,\"upgrades\":{\"talent\":[\"crackshot\",\"heroic\"]}},{\"id\":\"tallissanlintra\",\"ship\":\"rz2awing\",\"points\":36,\"upgrades\":{\"talent\":[\"crackshot\"]}},{\"id\":\"bluesquadronrecruit\",\"ship\":\"rz2awing\",\"points\":37,\"upgrades\":{\"talent\":[\"crackshot\"],\"tech\":[\"advancedoptics\"]}}],\"points\":186,\"vendor\":{\"yasb\":{\"builder\":\"(Yet Another) X-Wing Miniatures Squad Builder\",\"builder_url\":\"https://raithos.github.io\",\"link\":\"https://raithos.github.io/?f=Resistance&d=v6!h=200!231:172,5,,175,,171,168:U.12;239:116,172,,:;240:116,,,:;301:116,,186:&sn=Poe%20%2B%203A&obs=\"}},\"version\":\"2.0.0\",\"name\":\"Poe + 3A\"}"}, {"id": 11033, "name": "Vianello Mattia", "tournament_id": 555, "score": 4, "swiss_rank": 12, "top_cut_rank": null, "mov": 1514, "sos": "0.63", "dropped": false, "list_points": null, "list_json": "{\"faction\":\"separatistalliance\",\"pilots\":[{\"id\":\"tradefederationdrone\",\"ship\":\"vultureclassdroidfighter\",\"upgrades\":{\"missile\":[\"energyshellcharges\"]},\"points\":24},{\"id\":\"tradefederationdrone\",\"ship\":\"vultureclassdroidfighter\",\"upgrades\":{\"missile\":[\"energyshellcharges\"]},\"points\":24},{\"id\":\"tradefederationdrone\",\"ship\":\"vultureclassdroidfighter\",\"upgrades\":{\"missile\":[\"energyshellcharges\"]},\"points\":24},{\"id\":\"tradefederationdrone\",\"ship\":\"vultureclassdroidfighter\",\"upgrades\":{\"missile\":[\"energyshellcharges\"]},\"points\":24},{\"id\":\"tradefederationdrone\",\"ship\":\"vultureclassdroidfighter\",\"upgrades\":{\"missile\":[\"energyshellcharges\"]},\"points\":24},{\"id\":\"darthmaul\",\"ship\":\"sithinfiltrator\",\"upgrades\":{\"cannon\":[\"tractorbeam\"],\"crew\":[\"generalgrievous\"],\"device\":[\"drk1probedroids\"],\"force-power\":[\"hate\"]},\"points\":79}],\"name\":\"Maul and 5x Droids\",\"description\":\"\",\"points\":199,\"vendor\":{\"sb2xws\":{\"builder\":\"SB2XWS\",\"url\":\"http://sb2xws.herokuapp.com/translate/1ee7eb4e-e63d-4daf-8838-176af590c62e\"}}}"}, {"id": 11038, "name": "Rasulo Samuele", "tournament_id": 555, "score": 4, "swiss_rank": 17, "top_cut_rank": null, "mov": 1448, "sos": "0.56", "dropped": false, "list_points": null, "list_json": "{\"faction\":\"galacticempire\",\"pilots\":[{\"id\":\"darthvader\",\"ship\":\"tieadvancedx1\",\"upgrades\":{\"sensor\":[\"firecontrolsystem\"],\"modification\":[\"afterburners\"],\"force-power\":[\"hate\"]},\"points\":76},{\"id\":\"soontirfel\",\"ship\":\"tieininterceptor\",\"upgrades\":{\"modification\":[\"shieldupgrade\"],\"ept\":[\"outmaneuver\"]},\"points\":66},{\"id\":\"duchess\",\"ship\":\"tieskstriker\",\"upgrades\":{\"device\":[\"protonbombs\"]},\"points\":47}],\"name\":\"Lato Oscuro\",\"description\":\"\",\"points\":189,\"vendor\":{\"sb2xws\":{\"builder\":\"SB2XWS\",\"url\":\"http://sb2xws.herokuapp.com/translate/93085f81-adde-4a10-a77d-51eceed333ec\"}}}"}, {"id": 11057, "name": "Colombo Ian", "tournament_id": 555, "score": 3, "swiss_rank": 36, "top_cut_rank": null, "mov": 1368, "sos": "0.5", "dropped": false, "list_points": null, "list_json": "{\"faction\":\"scumandvillainy\",\"pilots\":[{\"id\":\"fennrau\",\"ship\":\"fangfighter\",\"points\":68},{\"id\":\"zealousrecruit\",\"ship\":\"fangfighter\",\"points\":44},{\"id\":\"zealousrecruit\",\"ship\":\"fangfighter\",\"points\":44},{\"id\":\"zealousrecruit\",\"ship\":\"fangfighter\",\"points\":44}],\"name\":\"1.\",\"description\":\"\",\"points\":200,\"vendor\":{\"sb2xws\":{\"builder\":\"SB2XWS\",\"url\":\"http://sb2xws.herokuapp.com/translate/ba0ff001-c303-48a0-abfa-8e97c7d74b08\"}}}"}, {"id": 11037, "name": "Terminiello Stefano", "tournament_id": 555, "score": 4, "swiss_rank": 16, "top_cut_rank": null, "mov": 1457, "sos": "0.51", "dropped": false, "list_points": null, "list_json": "{\"faction\":\"scumandvillainy\",\"pilots\":[{\"id\":\"fennrau\",\"ship\":\"fangfighter\",\"points\":68},{\"id\":\"bountyhunter\",\"ship\":\"firesprayclasspatrolcraft\",\"points\":66},{\"id\":\"bountyhunter\",\"ship\":\"firesprayclasspatrolcraft\",\"points\":66}],\"name\":\"1.\",\"description\":\"\",\"points\":200,\"vendor\":{\"sb2xws\":{\"builder\":\"SB2XWS\",\"url\":\"http://sb2xws.herokuapp.com/translate/ba0ff001-c303-48a0-abfa-8e97c7d74b08\"}}}"}, {"id": 11035, "name": "Bennati Matteo", "tournament_id": 555, "score": 4, "swiss_rank": 14, "top_cut_rank": null, "mov": 1477, "sos": "0.67", "dropped": false, "list_points": null, "list_json": "{\"faction\":\"scumandvillainy\",\"pilots\":[{\"id\":\"fennrau\",\"ship\":\"fangfighter\",\"points\":68},{\"id\":\"zealousrecruit\",\"ship\":\"fangfighter\",\"points\":44},{\"id\":\"bobafett\",\"ship\":\"firesprayclasspatrolcraft\",\"upgrades\":{\"title\":[\"slavei\"]},\"points\":88}],\"name\":\"1.\",\"description\":\"\",\"points\":200,\"vendor\":{\"sb2xws\":{\"builder\":\"SB2XWS\",\"url\":\"http://sb2xws.herokuapp.com/translate/ba0ff001-c303-48a0-abfa-8e97c7d74b08\"}}}"}, {"id": 11026, "name": "Di Vincenzo Liborio", "tournament_id": 555, "score": 5, "swiss_rank": 5, "top_cut_rank": 1, "mov": 1584, "sos": "0.58", "dropped": false, "list_points": null, "list_json": "{\"faction\":\"rebelalliance\",\"pilots\":[{\"id\":\"wedgeantilles\",\"ship\":\"t65xwing\",\"upgrades\":{\"configuration\":[\"servomotorsfoils\"]},\"points\":52},{\"id\":\"biggsdarklighter\",\"ship\":\"t65xwing\",\"upgrades\":{\"configuration\":[\"servomotorsfoils\"]},\"points\":48},{\"id\":\"cassianandor\",\"ship\":\"ut60duwing\",\"upgrades\":{\"crew\":[\"leiaorgana\"],\"configuration\":[\"pivotwing\"]},\"points\":49},{\"id\":\"braylenstramm\",\"ship\":\"asf01bwing\",\"upgrades\":{\"cannon\":[\"jammingbeam\"],\"ept\":[\"selfless\"]},\"points\":50}],\"name\":\"1.\",\"description\":\"\",\"points\":199,\"vendor\":{\"sb2xws\":{\"builder\":\"SB2XWS\",\"url\":\"http://sb2xws.herokuapp.com/translate/54131b7c-e2fa-47c2-9d16-88549d747767\"}}}"}, {"id": 11029, "name": "Mazzi Alessandro", "tournament_id": 555, "score": 5, "swiss_rank": 8, "top_cut_rank": 4, "mov": 1331, "sos": "0.63", "dropped": false, "list_points": null, "list_json": "{\"faction\":\"resistance\",\"pilots\":[{\"id\":\"lulolampar\",\"ship\":\"rz2awing\",\"upgrades\":{\"ept\":[\"crackshot\",\"predator\"]},\"points\":41},{\"id\":\"jessikapava\",\"ship\":\"t70xwing\",\"upgrades\":{\"configuration\":[\"integratedsfoils\"],\"astromech\":[\"bbastromech\"]},\"points\":55},{\"id\":\"jophseastriker\",\"ship\":\"t70xwing\",\"upgrades\":{\"configuration\":[\"integratedsfoils\"],\"ept\":[\"predator\"]},\"points\":54},{\"id\":\"redsquadronexpert\",\"ship\":\"t70xwing\",\"upgrades\":{\"configuration\":[\"integratedsfoils\"],\"ept\":[\"heroic\"]},\"points\":49}],\"name\":\"1.\",\"description\":\"\",\"points\":199,\"vendor\":{\"sb2xws\":{\"builder\":\"SB2XWS\",\"url\":\"http://sb2xws.herokuapp.com/translate/970e23a8-d78c-4d27-8dbd-331aa10a768f\"}}}"}, {"id": 11024, "name": "Scarfone Alessio", "tournament_id": 555, "score": 5, "swiss_rank": 3, "top_cut_rank": 4, "mov": 1706, "sos": "0.58", "dropped": false, "list_points": null, "list_json": "{\"faction\":\"rebelalliance\",\"pilots\":[{\"id\":\"wedgeantilles\",\"ship\":\"t65xwing\",\"upgrades\":{\"configuration\":[\"servomotorsfoils\"],\"ept\":[\"predator\"]},\"points\":54},{\"id\":\"cassianandor\",\"ship\":\"ut60duwing\",\"upgrades\":{\"crew\":[\"tacticalofficer\",\"leiaorgana\"]},\"points\":51},{\"id\":\"braylenstramm\",\"ship\":\"asf01bwing\",\"upgrades\":{\"cannon\":[\"jammingbeam\"],\"modification\":[\"hullupgrade\"]},\"points\":50},{\"id\":\"bluesquadronpilot\",\"ship\":\"asf01bwing\",\"upgrades\":{\"cannon\":[\"jammingbeam\"],\"modification\":[\"hullupgrade\"]},\"points\":44}],\"name\":\"1.\",\"description\":\"\",\"points\":199,\"vendor\":{\"sb2xws\":{\"builder\":\"SB2XWS\",\"url\":\"http://sb2xws.herokuapp.com/translate/859afcd2-d2a4-46f7-9bf2-d4408893df57\"}}}"}, {"id": 11023, "name": "Marmorini Alessandro", "tournament_id": 555, "score": 5, "swiss_rank": 2, "top_cut_rank": 2, "mov": 1719, "sos": "0.53", "dropped": false, "list_points": null, "list_json": "{\"faction\":\"rebelalliance\",\"pilots\":[{\"id\":\"wedgeantilles\",\"ship\":\"t65xwing\",\"upgrades\":{\"modification\":[\"hullupgrade\"],\"configuration\":[\"servomotorsfoils\"],\"ept\":[\"predator\"]},\"points\":59},{\"id\":\"bluesquadronscout\",\"ship\":\"ut60duwing\",\"upgrades\":{\"crew\":[\"tacticalofficer\",\"leiaorgana\"],\"modification\":[\"hullupgrade\"],\"configuration\":[\"pivotwing\"]},\"points\":52},{\"id\":\"bluesquadronpilot\",\"ship\":\"asf01bwing\",\"upgrades\":{\"modification\":[\"hullupgrade\"]},\"points\":44},{\"id\":\"bluesquadronpilot\",\"ship\":\"asf01bwing\",\"upgrades\":{\"modification\":[\"hullupgrade\"]},\"points\":44}],\"name\":\"1.\",\"description\":\"\",\"points\":199,\"vendor\":{\"sb2xws\":{\"builder\":\"SB2XWS\",\"url\":\"http://sb2xws.herokuapp.com/translate/859afcd2-d2a4-46f7-9bf2-d4408893df57\"}}}"}, {"id": 11028, "name": "Guadagnini Nicol\ufffd", "tournament_id": 555, "score": 5, "swiss_rank": 7, "top_cut_rank": 8, "mov": 1527, "sos": "0.56", "dropped": false, "list_points": null, "list_json": "{\"faction\":\"rebelalliance\",\"pilots\":[{\"id\":\"wedgeantilles\",\"ship\":\"t65xwing\",\"upgrades\":{\"configuration\":[\"servomotorsfoils\"],\"ept\":[\"swarmtactics\"]},\"points\":55},{\"id\":\"braylenstramm\",\"ship\":\"asf01bwing\",\"upgrades\":{\"cannon\":[\"jammingbeam\",\"tractorbeam\"],\"ept\":[\"swarmtactics\"]},\"points\":52},{\"id\":\"bladesquadronveteran\",\"ship\":\"asf01bwing\",\"upgrades\":{\"cannon\":[\"jammingbeam\",\"tractorbeam\"],\"ept\":[\"swarmtactics\"]},\"points\":48},{\"id\":\"bluesquadronpilot\",\"ship\":\"asf01bwing\",\"upgrades\":{\"cannon\":[\"jammingbeam\",\"tractorbeam\"]},\"points\":43}],\"name\":\"1.\",\"description\":\"\",\"points\":198,\"vendor\":{\"sb2xws\":{\"builder\":\"SB2XWS\",\"url\":\"http://sb2xws.herokuapp.com/translate/e2020611-32a0-46c8-8e61-e60e7df35514\"}}}"}, {"id": 11025, "name": "Canali Giacomo", "tournament_id": 555, "score": 5, "swiss_rank": 4, "top_cut_rank": 8, "mov": 1595, "sos": "0.42", "dropped": false, "list_points": null, "list_json": "{\"faction\":\"rebelalliance\",\"pilots\":[{\"id\":\"greensquadronpilot\",\"ship\":\"rz1awing\",\"upgrades\":{\"missile\":[\"protonrockets\"],\"ept\":[\"crackshot\",\"predator\"]},\"points\":42},{\"id\":\"greensquadronpilot\",\"ship\":\"rz1awing\",\"upgrades\":{\"missile\":[\"protonrockets\"],\"ept\":[\"crackshot\",\"predator\"]},\"points\":42},{\"id\":\"sawgerrera\",\"ship\":\"ut60duwing\",\"upgrades\":{\"crew\":[\"tacticalofficer\",\"leiaorgana\"],\"sensor\":[\"collisiondetector\"],\"ept\":[\"trickshot\"]},\"points\":64},{\"id\":\"tennumb\",\"ship\":\"asf01bwing\",\"upgrades\":{\"cannon\":[\"heavylasercannon\"],\"ept\":[\"predator\"]},\"points\":52}],\"name\":\"1.\",\"description\":\"\",\"points\":200,\"vendor\":{\"sb2xws\":{\"builder\":\"SB2XWS\",\"url\":\"http://sb2xws.herokuapp.com/translate/d7992160-9243-4dd4-b9d7-525ffd044027\"}}}"}, {"id": 11027, "name": "Landini Tommaso", "tournament_id": 555, "score": 5, "swiss_rank": 6, "top_cut_rank": 8, "mov": 1556, "sos": "0.56", "dropped": false, "list_points": null, "list_json": "{\"faction\":\"galacticrepublic\",\"pilots\":[{\"id\":\"macewindu\",\"ship\":\"delta7aethersprite\",\"upgrades\":{\"force-power\":[\"sense\"],\"configuration\":[\"delta7b\"],\"astromech\":[\"r2astromech\"]},\"points\":72},{\"id\":\"saeseetiin\",\"ship\":\"delta7aethersprite\",\"upgrades\":{\"configuration\":[\"delta7b\"],\"astromech\":[\"r2astromech\"]},\"points\":64},{\"id\":\"luminaraunduli\",\"ship\":\"delta7aethersprite\",\"upgrades\":{\"configuration\":[\"delta7b\"],\"astromech\":[\"r2astromech\"]},\"points\":64}],\"name\":\"1.\",\"description\":\"\",\"points\":200,\"vendor\":{\"sb2xws\":{\"builder\":\"SB2XWS\",\"url\":\"http://sb2xws.herokuapp.com/translate/73d2348f-529d-486e-a77b-73d8fbf94b0c\"}}}"}, {"id": 11022, "name": "Fiore Stefano", "tournament_id": 555, "score": 6, "swiss_rank": 1, "top_cut_rank": 8, "mov": 1584, "sos": "0.61", "dropped": false, "list_points": null, "list_json": "{\"faction\":\"galacticempire\",\"pilots\":[{\"id\":\"duchess\",\"ship\":\"tieskstriker\",\"upgrades\":{\"modification\":[\"hullupgrade\"],\"device\":[\"proximitymines\"],\"ept\":[\"predator\"]},\"points\":55},{\"id\":\"soontirfel\",\"ship\":\"tieininterceptor\",\"upgrades\":{\"modification\":[\"shieldupgrade\"],\"ept\":[\"predator\"]},\"points\":62},{\"id\":\"darthvader\",\"ship\":\"tieadvancedx1\",\"upgrades\":{\"sensor\":[\"firecontrolsystem\"],\"modification\":[\"afterburners\"]},\"points\":73}],\"name\":\"1.\",\"description\":\"\",\"points\":190,\"vendor\":{\"sb2xws\":{\"builder\":\"SB2XWS\",\"url\":\"http://sb2xws.herokuapp.com/translate/885134d6-aafd-4137-89b9-557d8bed1c23\"}}}"}, {"id": 11096, "name": "Colombo N.M.", "tournament_id": 555, "score": 0, "swiss_rank": 0, "top_cut_rank": null, "mov": 210, "sos": "0.67", "dropped": null, "list_points": null, "list_json": null}, {"id": 11095, "name": "Desco Marco", "tournament_id": 555, "score": 0, "swiss_rank": 0, "top_cut_rank": null, "mov": 231, "sos": "0.67", "dropped": null, "list_points": null, "list_json": null}, {"id": 11094, "name": "Negri Corrado", "tournament_id": 555, "score": 0, "swiss_rank": 0, "top_cut_rank": null, "mov": 692, "sos": "0.47", "dropped": null, "list_points": null, "list_json": null}, {"id": 11093, "name": "Stevanato Alessio", "tournament_id": 555, "score": 0, "swiss_rank": 70, "top_cut_rank": null, "mov": 795, "sos": "0.36", "dropped": null, "list_points": null, "list_json": null}, {"id": 11092, "name": "Venegoni Loris", "tournament_id": 555, "score": 1, "swiss_rank": 0, "top_cut_rank": null, "mov": 274, "sos": "0.46", "dropped": null, "list_points": null, "list_json": null}, {"id": 11091, "name": "Amodeo Alessandro", "tournament_id": 555, "score": 1, "swiss_rank": 0, "top_cut_rank": null, "mov": 624, "sos": "0.42", "dropped": null, "list_points": null, "list_json": null}, {"id": 11090, "name": "Magistroni Matteo", "tournament_id": 555, "score": 1, "swiss_rank": 69, "top_cut_rank": null, "mov": 707, "sos": "0.39", "dropped": null, "list_points": null, "list_json": null}, {"id": 11089, "name": "Lazzari Massimiliano", "tournament_id": 555, "score": 1, "swiss_rank": 68, "top_cut_rank": null, "mov": 736, "sos": "0.44", "dropped": null, "list_points": null, "list_json": null}, {"id": 11088, "name": "Bertolo Greta", "tournament_id": 555, "score": 1, "swiss_rank": 67, "top_cut_rank": null, "mov": 808, "sos": "0.35", "dropped": null, "list_points": null, "list_json": null}, {"id": 11087, "name": "Bagnasco Alessio", "tournament_id": 555, "score": 2, "swiss_rank": 66, "top_cut_rank": null, "mov": 725, "sos": "0.61", "dropped": null, "list_points": null, "list_json": null}, {"id": 11086, "name": "Mazzarelli Marco", "tournament_id": 555, "score": 2, "swiss_rank": 65, "top_cut_rank": null, "mov": 803, "sos": "0.54", "dropped": null, "list_points": null, "list_json": null}, {"id": 11085, "name": "Tiraboschi Fabio", "tournament_id": 555, "score": 2, "swiss_rank": 64, "top_cut_rank": null, "mov": 828, "sos": "0.53", "dropped": null, "list_points": null, "list_json": null}, {"id": 11084, "name": "Gubernati Luca", "tournament_id": 555, "score": 2, "swiss_rank": 63, "top_cut_rank": null, "mov": 862, "sos": "0.58", "dropped": null, "list_points": null, "list_json": null}, {"id": 11083, "name": "Fioravanti Davide", "tournament_id": 555, "score": 2, "swiss_rank": 62, "top_cut_rank": null, "mov": 904, "sos": "0.56", "dropped": null, "list_points": null, "list_json": null}, {"id": 11082, "name": "Moiso Roberto", "tournament_id": 555, "score": 2, "swiss_rank": 61, "top_cut_rank": null, "mov": 944, "sos": "0.39", "dropped": null, "list_points": null, "list_json": null}, {"id": 11081, "name": "Battistetti Corrado", "tournament_id": 555, "score": 2, "swiss_rank": 60, "top_cut_rank": null, "mov": 987, "sos": "0.5", "dropped": null, "list_points": null, "list_json": null}, {"id": 11080, "name": "Nitro ", "tournament_id": 555, "score": 2, "swiss_rank": 59, "top_cut_rank": null, "mov": 1012, "sos": "0.43", "dropped": null, "list_points": null, "list_json": null}, {"id": 11079, "name": "Del  Prato Enrico", "tournament_id": 555, "score": 2, "swiss_rank": 58, "top_cut_rank": null, "mov": 1017, "sos": "0.39", "dropped": null, "list_points": null, "list_json": null}, {"id": 11078, "name": "Salati Gabriele", "tournament_id": 555, "score": 2, "swiss_rank": 57, "top_cut_rank": null, "mov": 1033, "sos": "0.47", "dropped": null, "list_points": null, "list_json": null}, {"id": 11076, "name": "Grimi Ambrogio", "tournament_id": 555, "score": 2, "swiss_rank": 55, "top_cut_rank": null, "mov": 1083, "sos": "0.39", "dropped": null, "list_points": null, "list_json": null}, {"id": 11075, "name": "Bona Federico", "tournament_id": 555, "score": 2, "swiss_rank": 54, "top_cut_rank": null, "mov": 1106, "sos": "0.28", "dropped": null, "list_points": null, "list_json": null}, {"id": 11073, "name": "Loss Tommaso", "tournament_id": 555, "score": 2, "swiss_rank": 52, "top_cut_rank": null, "mov": 1268, "sos": "0.48", "dropped": null, "list_points": null, "list_json": null}, {"id": 11072, "name": "Bettinelli Maurizio", "tournament_id": 555, "score": 3, "swiss_rank": 51, "top_cut_rank": null, "mov": 904, "sos": "0.64", "dropped": null, "list_points": null, "list_json": null}, {"id": 11070, "name": "Ornago Andrea", "tournament_id": 555, "score": 3, "swiss_rank": 49, "top_cut_rank": null, "mov": 957, "sos": "0.61", "dropped": null, "list_points": null, "list_json": null}, {"id": 11069, "name": "Brambilla Fabio", "tournament_id": 555, "score": 3, "swiss_rank": 48, "top_cut_rank": null, "mov": 973, "sos": "0.44", "dropped": null, "list_points": null, "list_json": null}, {"id": 11067, "name": "Bitetto Giuseppe", "tournament_id": 555, "score": 3, "swiss_rank": 46, "top_cut_rank": null, "mov": 1090, "sos": "0.53", "dropped": null, "list_points": null, "list_json": null}, {"id": 11065, "name": "Giampaolo Davide", "tournament_id": 555, "score": 3, "swiss_rank": 44, "top_cut_rank": null, "mov": 1155, "sos": "0.57", "dropped": null, "list_points": null, "list_json": null}, {"id": 11064, "name": "Todino Eugenio", "tournament_id": 555, "score": 3, "swiss_rank": 43, "top_cut_rank": null, "mov": 1168, "sos": "0.42", "dropped": null, "list_points": null, "list_json": null}, {"id": 11062, "name": "Casabianca Pierpaolo", "tournament_id": 555, "score": 3, "swiss_rank": 41, "top_cut_rank": null, "mov": 1217, "sos": "0.5", "dropped": null, "list_points": null, "list_json": null}, {"id": 11061, "name": "Mariani Laura", "tournament_id": 555, "score": 3, "swiss_rank": 40, "top_cut_rank": null, "mov": 1225, "sos": "0.47", "dropped": null, "list_points": null, "list_json": null}, {"id": 11060, "name": "Sghembri Dario", "tournament_id": 555, "score": 3, "swiss_rank": 39, "top_cut_rank": null, "mov": 1241, "sos": "0.47", "dropped": null, "list_points": null, "list_json": null}, {"id": 11058, "name": "Crivaro Marco", "tournament_id": 555, "score": 3, "swiss_rank": 37, "top_cut_rank": null, "mov": 1294, "sos": "0.7", "dropped": true, "list_points": null, "list_json": null}, {"id": 11056, "name": "Bevione Alessandro", "tournament_id": 555, "score": 3, "swiss_rank": 35, "top_cut_rank": null, "mov": 1369, "sos": "0.47", "dropped": null, "list_points": null, "list_json": null}, {"id": 11055, "name": "Cleva Mirco", "tournament_id": 555, "score": 3, "swiss_rank": 34, "top_cut_rank": null, "mov": 1392, "sos": "0.61", "dropped": null, "list_points": null, "list_json": null}, {"id": 11054, "name": "Secchia Michele", "tournament_id": 555, "score": 3, "swiss_rank": 33, "top_cut_rank": null, "mov": 1396, "sos": "0.61", "dropped": null, "list_points": null, "list_json": null}, {"id": 11052, "name": "Galasso Luca", "tournament_id": 555, "score": 3, "swiss_rank": 31, "top_cut_rank": null, "mov": 1430, "sos": "0.34", "dropped": null, "list_points": null, "list_json": null}, {"id": 11051, "name": "Molinero Mattia", "tournament_id": 555, "score": 3, "swiss_rank": 30, "top_cut_rank": null, "mov": 1444, "sos": "0.28", "dropped": null, "list_points": null, "list_json": null}, {"id": 11050, "name": "Makuc Damjan", "tournament_id": 555, "score": 3, "swiss_rank": 29, "top_cut_rank": null, "mov": 1457, "sos": "0.61", "dropped": null, "list_points": null, "list_json": null}, {"id": 11048, "name": "Puglia Andrea", "tournament_id": 555, "score": 4, "swiss_rank": 27, "top_cut_rank": null, "mov": 1041, "sos": "0.58", "dropped": null, "list_points": null, "list_json": null}, {"id": 11046, "name": "Rossetti Marco", "tournament_id": 555, "score": 4, "swiss_rank": 25, "top_cut_rank": null, "mov": 1234, "sos": "0.56", "dropped": null, "list_points": null, "list_json": null}, {"id": 11045, "name": "Ambrosio Flavio", "tournament_id": 555, "score": 4, "swiss_rank": 24, "top_cut_rank": null, "mov": 1307, "sos": "0.5", "dropped": null, "list_points": null, "list_json": null}, {"id": 11044, "name": "Tozzi Carlo", "tournament_id": 555, "score": 4, "swiss_rank": 23, "top_cut_rank": null, "mov": 1332, "sos": "0.64", "dropped": null, "list_points": null, "list_json": null}, {"id": 11043, "name": "Muraglia Gabriele", "tournament_id": 555, "score": 4, "swiss_rank": 22, "top_cut_rank": null, "mov": 1339, "sos": "0.44", "dropped": null, "list_points": null, "list_json": null}, {"id": 11042, "name": "Peano Carlo", "tournament_id": 555, "score": 4, "swiss_rank": 21, "top_cut_rank": null, "mov": 1344, "sos": "0.53", "dropped": null, "list_points": null, "list_json": null}, {"id": 11041, "name": "Molteni Andrea", "tournament_id": 555, "score": 4, "swiss_rank": 20, "top_cut_rank": null, "mov": 1358, "sos": "0.39", "dropped": null, "list_points": null, "list_json": null}, {"id": 11040, "name": "Arosio Giacomo", "tournament_id": 555, "score": 4, "swiss_rank": 19, "top_cut_rank": null, "mov": 1383, "sos": "0.53", "dropped": null, "list_points": null, "list_json": null}, {"id": 11039, "name": "Milan Davide", "tournament_id": 555, "score": 4, "swiss_rank": 18, "top_cut_rank": null, "mov": 1413, "sos": "0.56", "dropped": null, "list_points": null, "list_json": null}, {"id": 11032, "name": "Minzolini Mattia", "tournament_id": 555, "score": 4, "swiss_rank": 11, "top_cut_rank": null, "mov": 1529, "sos": "0.53", "dropped": null, "list_points": null, "list_json": null}, {"id": 11031, "name": "Pezzutto Roberto", "tournament_id": 555, "score": 4, "swiss_rank": 10, "top_cut_rank": null, "mov": 1559, "sos": "0.58", "dropped": null, "list_points": null, "list_json": null}], "rounds": [{"id": 394, "tournament_id": 555, "roundtype_id": 2, "round_number": 2, "matches": [{"id": 6745, "player1_id": 11026, "player1_points": 200, "player2_id": 11023, "player2_points": 0, "result": "win", "winner_id": 11026}]}, {"id": 393, "tournament_id": 555, "roundtype_id": 2, "round_number": 4, "matches": [{"id": 6744, "player1_id": 11024, "player1_points": 0, "player2_id": 11023, "player2_points": 200, "result": "win", "winner_id": 11023}, {"id": 6743, "player1_id": 11029, "player1_points": 0, "player2_id": 11026, "player2_points": 200, "result": "win", "winner_id": 11026}]}, {"id": 392, "tournament_id": 555, "roundtype_id": 2, "round_number": 8, "matches": [{"id": 6742, "player1_id": 11023, "player1_points": 200, "player2_id": 11028, "player2_points": 0, "result": "win", "winner_id": 11023}, {"id": 6741, "player1_id": 11024, "player1_points": 200, "player2_id": 11027, "player2_points": 0, "result": "win", "winner_id": 11024}, {"id": 6740, "player1_id": 11025, "player1_points": 0, "player2_id": 11026, "player2_points": 200, "result": "win", "winner_id": 11026}, {"id": 6739, "player1_id": 11022, "player1_points": 0, "player2_id": 11029, "player2_points": 200, "result": "win", "winner_id": 11029}]}, {"id": 391, "tournament_id": 555, "roundtype_id": 1, "round_number": 6, "matches": [{"id": 6738, "player1_id": 11079, "player1_points": 98, "player2_id": 11093, "player2_points": 52, "result": "win", "winner_id": 11079}, {"id": 6737, "player1_id": 11088, "player1_points": 0, "player2_id": 11075, "player2_points": 200, "result": "win", "winner_id": 11075}, {"id": 6736, "player1_id": 11074, "player1_points": 200, "player2_id": 11089, "player2_points": 0, "result": "win", "winner_id": 11074}, {"id": 6735, "player1_id": 11090, "player1_points": 78, "player2_id": 11080, "player2_points": 165, "result": "win", "winner_id": 11080}, {"id": 6734, "player1_id": 11052, "player1_points": 98, "player2_id": 11077, "player2_points": 68, "result": "win", "winner_id": 11052}, {"id": 6733, "player1_id": 11059, "player1_points": 200, "player2_id": 11086, "player2_points": 0, "result": "win", "winner_id": 11059}, {"id": 6732, "player1_id": 11060, "player1_points": 140, "player2_id": 11065, "player2_points": 107, "result": "win", "winner_id": 11060}, {"id": 6731, "player1_id": 11058, "player1_points": 200, "player2_id": 11084, "player2_points": 0, "result": "win", "winner_id": 11058}, {"id": 6730, "player1_id": 11061, "player1_points": 200, "player2_id": 11083, "player2_points": 44, "result": "win", "winner_id": 11061}, {"id": 6729, "player1_id": 11078, "player1_points": 90, "player2_id": 11064, "player2_points": 200, "result": "win", "winner_id": 11064}, {"id": 6728, "player1_id": 11087, "player1_points": 0, "player2_id": 11066, "player2_points": 200, "result": "win", "winner_id": 11066}, {"id": 6727, "player1_id": 11085, "player1_points": 49, "player2_id": 11051, "player2_points": 200, "result": "win", "winner_id": 11051}, {"id": 6726, "player1_id": 11067, "player1_points": 200, "player2_id": 11081, "player2_points": 73, "result": "win", "winner_id": 11067}, {"id": 6725, "player1_id": 11049, "player1_points": 150, "player2_id": 11076, "player2_points": 80, "result": "win", "winner_id": 11049}, {"id": 6724, "player1_id": 11068, "player1_points": 200, "player2_id": 11073, "player2_points": 109, "result": "win", "winner_id": 11068}, {"id": 6723, "player1_id": 11043, "player1_points": 141, "player2_id": 11082, "player2_points": 105, "result": "win", "winner_id": 11043}, {"id": 6722, "player1_id": 11047, "player1_points": 200, "player2_id": 11055, "player2_points": 125, "result": "win", "winner_id": 11047}, {"id": 6721, "player1_id": 11072, "player1_points": 77, "player2_id": 11039, "player2_points": 200, "result": "win", "winner_id": 11039}, {"id": 6720, "player1_id": 11062, "player1_points": 101, "player2_id": 11037, "player2_points": 132, "result": "win", "winner_id": 11037}, {"id": 6719, "player1_id": 11032, "player1_points": 200, "player2_id": 11056, "player2_points": 96, "result": "win", "winner_id": 11032}, {"id": 6718, "player1_id": 11057, "player1_points": 102, "player2_id": 11050, "player2_points": 88, "result": "win", "winner_id": 11057}, {"id": 6717, "player1_id": 11053, "player1_points": 153, "player2_id": 11046, "player2_points": 170, "result": "win", "winner_id": 11046}, {"id": 6716, "player1_id": 11048, "player1_points": 144, "player2_id": 11054, "player2_points": 127, "result": "win", "winner_id": 11048}, {"id": 6715, "player1_id": 11069, "player1_points": 49, "player2_id": 11031, "player2_points": 200, "result": "win", "winner_id": 11031}, {"id": 6714, "player1_id": 11045, "player1_points": 200, "player2_id": 11063, "player2_points": 105, "result": "win", "winner_id": 11045}, {"id": 6713, "player1_id": 11034, "player1_points": 200, "player2_id": 11071, "player2_points": 0, "result": "win", "winner_id": 11034}, {"id": 6712, "player1_id": 11041, "player1_points": 200, "player2_id": 11070, "player2_points": 177, "result": "win", "winner_id": 11041}, {"id": 6711, "player1_id": 11042, "player1_points": 101, "player2_id": 11044, "player2_points": 200, "result": "win", "winner_id": 11044}, {"id": 6710, "player1_id": 11025, "player1_points": 188, "player2_id": 11033, "player2_points": 121, "result": "win", "winner_id": 11025}, {"id": 6709, "player1_id": 11030, "player1_points": 64, "player2_id": 11027, "player2_points": 95, "result": "win", "winner_id": 11027}, {"id": 6708, "player1_id": 11029, "player1_points": 147, "player2_id": 11040, "player2_points": 79, "result": "win", "winner_id": 11029}, {"id": 6707, "player1_id": 11036, "player1_points": 80, "player2_id": 11028, "player2_points": 200, "result": "win", "winner_id": 11028}, {"id": 6706, "player1_id": 11023, "player1_points": 144, "player2_id": 11035, "player2_points": 88, "result": "win", "winner_id": 11023}, {"id": 6705, "player1_id": 11038, "player1_points": 125, "player2_id": 11024, "player2_points": 156, "result": "win", "winner_id": 11024}, {"id": 6704, "player1_id": 11026, "player1_points": 123, "player2_id": 11022, "player2_points": 126, "result": "win", "winner_id": 11022}]}, {"id": 390, "tournament_id": 555, "roundtype_id": 1, "round_number": 5, "matches": [{"id": 6703, "player1_id": 11088, "player1_points": 200, "player2_id": 11093, "player2_points": 118, "result": "win", "winner_id": 11088}, {"id": 6702, "player1_id": 11049, "player1_points": 200, "player2_id": 11094, "player2_points": 0, "result": "win", "winner_id": 11049}, {"id": 6701, "player1_id": 11079, "player1_points": 70, "player2_id": 11061, "player2_points": 200, "result": "win", "winner_id": 11061}, {"id": 6700, "player1_id": 11052, "player1_points": 133, "player2_id": 11080, "player2_points": 81, "result": "win", "winner_id": 11052}, {"id": 6699, "player1_id": 11090, "player1_points": 75, "player2_id": 11076, "player2_points": 200, "result": "win", "winner_id": 11076}, {"id": 6698, "player1_id": 11089, "player1_points": 49, "player2_id": 11051, "player2_points": 173, "result": "win", "winner_id": 11051}, {"id": 6697, "player1_id": 11082, "player1_points": 96, "player2_id": 11074, "player2_points": 92, "result": "win", "winner_id": 11082}, {"id": 6696, "player1_id": 11091, "player1_points": 121, "player2_id": 11077, "player2_points": 124, "result": "win", "winner_id": 11077}, {"id": 6695, "player1_id": 11064, "player1_points": 65, "player2_id": 11075, "player2_points": 42, "result": "win", "winner_id": 11064}, {"id": 6694, "player1_id": 11060, "player1_points": 110, "player2_id": 11059, "player2_points": 131, "result": "win", "winner_id": 11059}, {"id": 6693, "player1_id": 11067, "player1_points": 49, "player2_id": 11031, "player2_points": 200, "result": "win", "winner_id": 11031}, {"id": 6692, "player1_id": 11041, "player1_points": 200, "player2_id": 11073, "player2_points": 85, "result": "win", "winner_id": 11041}, {"id": 6691, "player1_id": 11055, "player1_points": 200, "player2_id": 11068, "player2_points": 23, "result": "win", "winner_id": 11055}, {"id": 6690, "player1_id": 11066, "player1_points": 117, "player2_id": 11056, "player2_points": 200, "result": "win", "winner_id": 11056}, {"id": 6689, "player1_id": 11057, "player1_points": 63, "player2_id": 11065, "player2_points": 78, "result": "win", "winner_id": 11065}, {"id": 6688, "player1_id": 11072, "player1_points": 200, "player2_id": 11085, "player2_points": 134, "result": "win", "winner_id": 11072}, {"id": 6687, "player1_id": 11078, "player1_points": 19, "player2_id": 11063, "player2_points": 200, "result": "win", "winner_id": 11063}, {"id": 6686, "player1_id": 11069, "player1_points": 149, "player2_id": 11083, "player2_points": 138, "result": "win", "winner_id": 11069}, {"id": 6685, "player1_id": 11045, "player1_points": 200, "player2_id": 11087, "player2_points": 116, "result": "win", "winner_id": 11045}, {"id": 6684, "player1_id": 11081, "player1_points": 49, "player2_id": 11054, "player2_points": 147, "result": "win", "winner_id": 11054}, {"id": 6683, "player1_id": 11032, "player1_points": 200, "player2_id": 11086, "player2_points": 48, "result": "win", "winner_id": 11032}, {"id": 6682, "player1_id": 11084, "player1_points": 119, "player2_id": 11062, "player2_points": 200, "result": "win", "winner_id": 11062}, {"id": 6681, "player1_id": 11047, "player1_points": 145, "player2_id": 11058, "player2_points": 87, "result": "win", "winner_id": 11047}, {"id": 6680, "player1_id": 11043, "player1_points": 80, "player2_id": 11050, "player2_points": 156, "result": "win", "winner_id": 11050}, {"id": 6679, "player1_id": 11044, "player1_points": 136, "player2_id": 11027, "player2_points": 143, "result": "win", "winner_id": 11027}, {"id": 6678, "player1_id": 11025, "player1_points": 200, "player2_id": 11070, "player2_points": 42, "result": "win", "winner_id": 11025}, {"id": 6677, "player1_id": 11042, "player1_points": 200, "player2_id": 11034, "player2_points": 92, "result": "win", "winner_id": 11042}, {"id": 6676, "player1_id": 11029, "player1_points": 200, "player2_id": 11037, "player2_points": 125, "result": "win", "winner_id": 11029}, {"id": 6675, "player1_id": 11038, "player1_points": 40, "player2_id": 11071, "player2_points": 24, "result": "win", "winner_id": 11038}, {"id": 6674, "player1_id": 11040, "player1_points": 98, "player2_id": 11053, "player2_points": 96, "result": "win", "winner_id": 11040}, {"id": 6673, "player1_id": 11046, "player1_points": 176, "player2_id": 11028, "player2_points": 200, "result": "win", "winner_id": 11028}, {"id": 6672, "player1_id": 11036, "player1_points": 200, "player2_id": 11039, "player2_points": 48, "result": "win", "winner_id": 11036}, {"id": 6671, "player1_id": 11048, "player1_points": 44, "player2_id": 11023, "player2_points": 200, "result": "win", "winner_id": 11023}, {"id": 6670, "player1_id": 11024, "player1_points": 38, "player2_id": 11030, "player2_points": 96, "result": "win", "winner_id": 11030}, {"id": 6669, "player1_id": 11035, "player1_points": 55, "player2_id": 11022, "player2_points": 200, "result": "win", "winner_id": 11022}, {"id": 6668, "player1_id": 11033, "player1_points": 98, "player2_id": 11026, "player2_points": 120, "result": "win", "winner_id": 11026}]}, {"id": 389, "tournament_id": 555, "roundtype_id": 1, "round_number": 4, "matches": [{"id": 6667, "player1_id": 11080, "player1_points": 0, "player2_id": null, "player2_points": null, "result": "bye", "winner_id": null}, {"id": 6666, "player1_id": 11049, "player1_points": 200, "player2_id": 11088, "player2_points": 100, "result": "win", "winner_id": 11049}, {"id": 6665, "player1_id": 11075, "player1_points": 152, "player2_id": 11094, "player2_points": 112, "result": "win", "winner_id": 11075}, {"id": 6664, "player1_id": 11093, "player1_points": 138, "player2_id": 11082, "player2_points": 152, "result": "win", "winner_id": 11082}, {"id": 6663, "player1_id": 11063, "player1_points": 156, "player2_id": 11051, "player2_points": 146, "result": "win", "winner_id": 11063}, {"id": 6662, "player1_id": 11074, "player1_points": 85, "player2_id": 11041, "player2_points": 127, "result": "win", "winner_id": 11041}, {"id": 6661, "player1_id": 11090, "player1_points": 73, "player2_id": 11047, "player2_points": 105, "result": "win", "winner_id": 11047}, {"id": 6660, "player1_id": 11076, "player1_points": 105, "player2_id": 11068, "player2_points": 200, "result": "win", "winner_id": 11068}, {"id": 6659, "player1_id": 11044, "player1_points": 161, "player2_id": 11077, "player2_points": 122, "result": "win", "winner_id": 11044}, {"id": 6658, "player1_id": 11052, "player1_points": 101, "player2_id": 11069, "player2_points": 107, "result": "win", "winner_id": 11069}, {"id": 6657, "player1_id": 11085, "player1_points": 98, "player2_id": 11089, "player2_points": 74, "result": "win", "winner_id": 11085}, {"id": 6656, "player1_id": 11059, "player1_points": 84, "player2_id": 11056, "player2_points": 200, "result": "win", "winner_id": 11056}, {"id": 6655, "player1_id": 11061, "player1_points": 76, "player2_id": 11084, "player2_points": 178, "result": "win", "winner_id": 11084}, {"id": 6654, "player1_id": 11079, "player1_points": 150, "player2_id": 11066, "player2_points": 151, "result": "win", "winner_id": 11066}, {"id": 6653, "player1_id": 11086, "player1_points": 200, "player2_id": 11092, "player2_points": 0, "result": "win", "winner_id": 11086}, {"id": 6652, "player1_id": 11091, "player1_points": 0, "player2_id": 11073, "player2_points": 200, "result": "win", "winner_id": 11073}, {"id": 6651, "player1_id": 11032, "player1_points": 200, "player2_id": 11064, "player2_points": 32, "result": "win", "winner_id": 11032}, {"id": 6650, "player1_id": 11072, "player1_points": 92, "player2_id": 11023, "player2_points": 200, "result": "win", "winner_id": 11023}, {"id": 6649, "player1_id": 11067, "player1_points": 74, "player2_id": 11030, "player2_points": 200, "result": "win", "winner_id": 11030}, {"id": 6648, "player1_id": 11040, "player1_points": 125, "player2_id": 11054, "player2_points": 101, "result": "win", "winner_id": 11040}, {"id": 6647, "player1_id": 11057, "player1_points": 147, "player2_id": 11025, "player2_points": 178, "result": "win", "winner_id": 11025}, {"id": 6646, "player1_id": 11070, "player1_points": 168, "player2_id": 11060, "player2_points": 166, "result": "win", "winner_id": 11070}, {"id": 6645, "player1_id": 11045, "player1_points": 0, "player2_id": 11027, "player2_points": 200, "result": "win", "winner_id": 11027}, {"id": 6644, "player1_id": 11062, "player1_points": 158, "player2_id": 11029, "player2_points": 200, "result": "win", "winner_id": 11029}, {"id": 6643, "player1_id": 11065, "player1_points": 98, "player2_id": 11031, "player2_points": 75, "result": "win", "winner_id": 11065}, {"id": 6642, "player1_id": 11071, "player1_points": 85, "player2_id": 11078, "player2_points": 60, "result": "win", "winner_id": 11071}, {"id": 6641, "player1_id": 11058, "player1_points": 69, "player2_id": 11028, "player2_points": 200, "result": "win", "winner_id": 11028}, {"id": 6640, "player1_id": 11043, "player1_points": 200, "player2_id": 11083, "player2_points": 57, "result": "win", "winner_id": 11043}, {"id": 6639, "player1_id": 11081, "player1_points": 77, "player2_id": 11048, "player2_points": 98, "result": "win", "winner_id": 11048}, {"id": 6638, "player1_id": 11050, "player1_points": 118, "player2_id": 11038, "player2_points": 127, "result": "win", "winner_id": 11038}, {"id": 6637, "player1_id": 11087, "player1_points": 68, "player2_id": 11039, "player2_points": 200, "result": "win", "winner_id": 11039}, {"id": 6636, "player1_id": 11034, "player1_points": 103, "player2_id": 11055, "player2_points": 49, "result": "win", "winner_id": 11034}, {"id": 6635, "player1_id": 11036, "player1_points": 54, "player2_id": 11024, "player2_points": 200, "result": "win", "winner_id": 11024}, {"id": 6634, "player1_id": 11042, "player1_points": 0, "player2_id": 11026, "player2_points": 200, "result": "win", "winner_id": 11026}, {"id": 6633, "player1_id": 11046, "player1_points": 0, "player2_id": 11022, "player2_points": 101, "result": "win", "winner_id": 11022}, {"id": 6632, "player1_id": 11053, "player1_points": 100, "player2_id": 11033, "player2_points": 167, "result": "win", "winner_id": 11033}, {"id": 6631, "player1_id": 11037, "player1_points": 100, "player2_id": 11035, "player2_points": 200, "result": "win", "winner_id": 11035}]}, {"id": 388, "tournament_id": 555, "roundtype_id": 1, "round_number": 3, "matches": [{"id": 6630, "player1_id": 11080, "player1_points": 0, "player2_id": 11079, "player2_points": 78, "result": "win", "winner_id": 11079}, {"id": 6629, "player1_id": 11094, "player1_points": 0, "player2_id": 11074, "player2_points": 0, "result": "win", "winner_id": null}, {"id": 6628, "player1_id": 11073, "player1_points": 137, "player2_id": 11082, "player2_points": 20, "result": "win", "winner_id": 11073}, {"id": 6627, "player1_id": 11089, "player1_points": 156, "player2_id": 11075, "player2_points": 77, "result": "win", "winner_id": 11089}, {"id": 6626, "player1_id": 11056, "player1_points": 200, "player2_id": 11093, "player2_points": 39, "result": "win", "winner_id": 11056}, {"id": 6625, "player1_id": 11049, "player1_points": 97, "player2_id": 11061, "player2_points": 120, "result": "win", "winner_id": 11061}, {"id": 6624, "player1_id": 11088, "player1_points": 124, "player2_id": 11069, "player2_points": 200, "result": "win", "winner_id": 11069}, {"id": 6623, "player1_id": 11095, "player1_points": 0, "player2_id": 11064, "player2_points": 200, "result": "win", "winner_id": 11064}, {"id": 6622, "player1_id": 11084, "player1_points": 98, "player2_id": 11040, "player2_points": 150, "result": "win", "winner_id": 11040}, {"id": 6621, "player1_id": 11047, "player1_points": 72, "player2_id": 11045, "player2_points": 200, "result": "win", "winner_id": 11045}, {"id": 6620, "player1_id": 11062, "player1_points": 161, "player2_id": 11077, "player2_points": 98, "result": "win", "winner_id": 11062}, {"id": 6619, "player1_id": 11058, "player1_points": 128, "player2_id": 11041, "player2_points": 102, "result": "win", "winner_id": 11058}, {"id": 6618, "player1_id": 11048, "player1_points": 200, "player2_id": 11068, "player2_points": 121, "result": "win", "winner_id": 11048}, {"id": 6617, "player1_id": 11060, "player1_points": 150, "player2_id": 11076, "player2_points": 138, "result": "win", "winner_id": 11060}, {"id": 6616, "player1_id": 11044, "player1_points": 164, "player2_id": 11065, "player2_points": 137, "result": "win", "winner_id": 11044}, {"id": 6615, "player1_id": 11057, "player1_points": 200, "player2_id": 11090, "player2_points": 0, "result": "win", "winner_id": 11057}, {"id": 6614, "player1_id": 11092, "player1_points": 0, "player2_id": 11030, "player2_points": 200, "result": "win", "winner_id": 11030}, {"id": 6613, "player1_id": 11023, "player1_points": 200, "player2_id": 11085, "player2_points": 88, "result": "win", "winner_id": 11023}, {"id": 6612, "player1_id": 11034, "player1_points": 200, "player2_id": 11063, "player2_points": 49, "result": "win", "winner_id": 11034}, {"id": 6611, "player1_id": 11032, "player1_points": 64, "player2_id": 11027, "player2_points": 128, "result": "win", "winner_id": 11027}, {"id": 6610, "player1_id": 11066, "player1_points": 0, "player2_id": 11038, "player2_points": 200, "result": "win", "winner_id": 11038}, {"id": 6609, "player1_id": 11052, "player1_points": 56, "player2_id": 11081, "player2_points": 81, "result": "win", "winner_id": 11081}, {"id": 6608, "player1_id": 11059, "player1_points": 120, "player2_id": 11043, "player2_points": 147, "result": "win", "winner_id": 11043}, {"id": 6607, "player1_id": 11051, "player1_points": 169, "player2_id": 11078, "player2_points": 188, "result": "win", "winner_id": 11078}, {"id": 6606, "player1_id": 11086, "player1_points": 32, "player2_id": 11025, "player2_points": 200, "result": "win", "winner_id": 11025}, {"id": 6605, "player1_id": 11091, "player1_points": 80, "player2_id": 11071, "player2_points": 172, "result": "win", "winner_id": 11071}, {"id": 6604, "player1_id": 11055, "player1_points": 165, "player2_id": 11028, "player2_points": 173, "result": "win", "winner_id": 11028}, {"id": 6603, "player1_id": 11022, "player1_points": 76, "player2_id": 11050, "player2_points": 54, "result": "win", "winner_id": 11022}, {"id": 6602, "player1_id": 11083, "player1_points": 73, "player2_id": 11026, "player2_points": 111, "result": "win", "winner_id": 11026}, {"id": 6601, "player1_id": 11036, "player1_points": 200, "player2_id": 11029, "player2_points": 0, "result": "win", "winner_id": 11036}, {"id": 6600, "player1_id": 11053, "player1_points": 200, "player2_id": 11072, "player2_points": 31, "result": "win", "winner_id": 11053}, {"id": 6599, "player1_id": 11042, "player1_points": 200, "player2_id": 11070, "player2_points": 59, "result": "win", "winner_id": 11042}, {"id": 6598, "player1_id": 11033, "player1_points": 152, "player2_id": 11031, "player2_points": 76, "result": "win", "winner_id": 11033}, {"id": 6597, "player1_id": 11024, "player1_points": 200, "player2_id": 11087, "player2_points": 22, "result": "win", "winner_id": 11024}, {"id": 6596, "player1_id": 11039, "player1_points": 156, "player2_id": 11035, "player2_points": 200, "result": "win", "winner_id": 11035}, {"id": 6595, "player1_id": 11037, "player1_points": 200, "player2_id": 11067, "player2_points": 133, "result": "win", "winner_id": 11037}, {"id": 6594, "player1_id": 11046, "player1_points": 49, "player2_id": 11054, "player2_points": 24, "result": "win", "winner_id": 11046}]}, {"id": 387, "tournament_id": 555, "roundtype_id": 1, "round_number": 2, "matches": [{"id": 6593, "player1_id": 11091, "player1_points": 0, "player2_id": null, "player2_points": null, "result": "bye", "winner_id": null}, {"id": 6592, "player1_id": 11088, "player1_points": 51, "player2_id": 11092, "player2_points": 92, "result": "win", "winner_id": 11092}, {"id": 6591, "player1_id": 11071, "player1_points": 169, "player2_id": 11069, "player2_points": 140, "result": "win", "winner_id": 11071}, {"id": 6590, "player1_id": 11093, "player1_points": 35, "player2_id": 11090, "player2_points": 72, "result": "win", "winner_id": 11090}, {"id": 6589, "player1_id": 11073, "player1_points": 150, "player2_id": 11076, "player2_points": 168, "result": "win", "winner_id": 11076}, {"id": 6588, "player1_id": 11064, "player1_points": 76, "player2_id": 11047, "player2_points": 122, "result": "win", "winner_id": 11047}, {"id": 6587, "player1_id": 11041, "player1_points": 46, "player2_id": 11094, "player2_points": 22, "result": "win", "winner_id": 11041}, {"id": 6586, "player1_id": 11049, "player1_points": 121, "player2_id": 11062, "player2_points": 140, "result": "win", "winner_id": 11062}, {"id": 6585, "player1_id": 11080, "player1_points": 26, "player2_id": 11040, "player2_points": 200, "result": "win", "winner_id": 11040}, {"id": 6584, "player1_id": 11075, "player1_points": 19, "player2_id": 11059, "player2_points": 78, "result": "win", "winner_id": 11059}, {"id": 6583, "player1_id": 11056, "player1_points": 177, "player2_id": 11043, "player2_points": 200, "result": "win", "winner_id": 11043}, {"id": 6582, "player1_id": 11095, "player1_points": 105, "player2_id": 11025, "player2_points": 113, "result": "win", "winner_id": 11025}, {"id": 6581, "player1_id": 11079, "player1_points": 127, "player2_id": 11063, "player2_points": 200, "result": "win", "winner_id": 11063}, {"id": 6580, "player1_id": 11081, "player1_points": 148, "player2_id": 11089, "player2_points": 73, "result": "win", "winner_id": 11081}, {"id": 6579, "player1_id": 11082, "player1_points": 105, "player2_id": 11077, "player2_points": 165, "result": "win", "winner_id": 11077}, {"id": 6578, "player1_id": 11096, "player1_points": 51, "player2_id": 11045, "player2_points": 200, "result": "win", "winner_id": 11045}, {"id": 6577, "player1_id": 11032, "player1_points": 60, "player2_id": 11074, "player2_points": 36, "result": "win", "winner_id": 11032}, {"id": 6576, "player1_id": 11070, "player1_points": 200, "player2_id": 11061, "player2_points": 167, "result": "win", "winner_id": 11070}, {"id": 6575, "player1_id": 11046, "player1_points": 100, "player2_id": 11060, "player2_points": 48, "result": "win", "winner_id": 11046}, {"id": 6574, "player1_id": 11022, "player1_points": 43, "player2_id": 11058, "player2_points": 0, "result": "win", "winner_id": 11022}, {"id": 6573, "player1_id": 11042, "player1_points": 123, "player2_id": 11066, "player2_points": 90, "result": "win", "winner_id": 11042}, {"id": 6572, "player1_id": 11065, "player1_points": 77, "player2_id": 11050, "player2_points": 200, "result": "win", "winner_id": 11050}, {"id": 6571, "player1_id": 11057, "player1_points": 60, "player2_id": 11053, "player2_points": 200, "result": "win", "winner_id": 11053}, {"id": 6570, "player1_id": 11083, "player1_points": 40, "player2_id": 11052, "player2_points": 38, "result": "win", "winner_id": 11083}, {"id": 6569, "player1_id": 11034, "player1_points": 54, "player2_id": 11024, "player2_points": 114, "result": "win", "winner_id": 11024}, {"id": 6568, "player1_id": 11051, "player1_points": 68, "player2_id": 11087, "player2_points": 114, "result": "win", "winner_id": 11087}, {"id": 6567, "player1_id": 11031, "player1_points": 80, "player2_id": 11038, "player2_points": 73, "result": "win", "winner_id": 11031}, {"id": 6566, "player1_id": 11029, "player1_points": 170, "player2_id": 11044, "player2_points": 124, "result": "win", "winner_id": 11029}, {"id": 6565, "player1_id": 11035, "player1_points": 200, "player2_id": 11084, "player2_points": 44, "result": "win", "winner_id": 11035}, {"id": 6564, "player1_id": 11054, "player1_points": 100, "player2_id": 11023, "player2_points": 87, "result": "win", "winner_id": 11054}, {"id": 6563, "player1_id": 11086, "player1_points": 40, "player2_id": 11033, "player2_points": 200, "result": "win", "winner_id": 11033}, {"id": 6562, "player1_id": 11027, "player1_points": 70, "player2_id": 11055, "player2_points": 136, "result": "win", "winner_id": 11055}, {"id": 6561, "player1_id": 11036, "player1_points": 175, "player2_id": 11048, "player2_points": 0, "result": "win", "winner_id": 11036}, {"id": 6560, "player1_id": 11068, "player1_points": 98, "player2_id": 11026, "player2_points": 200, "result": "win", "winner_id": 11026}, {"id": 6559, "player1_id": 11037, "player1_points": 200, "player2_id": 11085, "player2_points": 33, "result": "win", "winner_id": 11037}, {"id": 6558, "player1_id": 11028, "player1_points": 74, "player2_id": 11039, "player2_points": 161, "result": "win", "winner_id": 11039}, {"id": 6557, "player1_id": 11078, "player1_points": 73, "player2_id": 11067, "player2_points": 116, "result": "win", "winner_id": 11067}, {"id": 6556, "player1_id": 11030, "player1_points": 76, "player2_id": 11072, "player2_points": 77, "result": "win", "winner_id": 11072}]}, {"id": 386, "tournament_id": 555, "roundtype_id": 1, "round_number": 1, "matches": [{"id": 6555, "player1_id": 11033, "player1_points": 0, "player2_id": null, "player2_points": null, "result": "bye", "winner_id": null}, {"id": 6554, "player1_id": 11065, "player1_points": 0, "player2_id": null, "player2_points": null, "result": "bye", "winner_id": null}, {"id": 6553, "player1_id": 11023, "player1_points": 0, "player2_id": null, "player2_points": null, "result": "bye", "winner_id": null}, {"id": 6552, "player1_id": 11030, "player1_points": 0, "player2_id": null, "player2_points": null, "result": "bye", "winner_id": null}, {"id": 6551, "player1_id": 11029, "player1_points": 0, "player2_id": null, "player2_points": null, "result": "bye", "winner_id": null}, {"id": 6550, "player1_id": 11058, "player1_points": 0, "player2_id": null, "player2_points": null, "result": "bye", "winner_id": null}, {"id": 6549, "player1_id": 11085, "player1_points": 0, "player2_id": null, "player2_points": null, "result": "bye", "winner_id": null}, {"id": 6548, "player1_id": 11044, "player1_points": 163, "player2_id": 11041, "player2_points": 143, "result": "win", "winner_id": 11044}, {"id": 6547, "player1_id": 11081, "player1_points": 86, "player2_id": 11039, "player2_points": 153, "result": "win", "winner_id": 11039}, {"id": 6546, "player1_id": 11076, "player1_points": 67, "player2_id": 11086, "player2_points": 150, "result": "win", "winner_id": 11086}, {"id": 6545, "player1_id": 11091, "player1_points": 19, "player2_id": 11052, "player2_points": 200, "result": "win", "winner_id": 11052}, {"id": 6544, "player1_id": 11089, "player1_points": 32, "player2_id": 11027, "player2_points": 152, "result": "win", "winner_id": 11027}, {"id": 6543, "player1_id": 11077, "player1_points": 38, "player2_id": 11083, "player2_points": 88, "result": "win", "winner_id": 11083}, {"id": 6542, "player1_id": 11078, "player1_points": 200, "player2_id": 11075, "player2_points": 27, "result": "win", "winner_id": 11078}, {"id": 6541, "player1_id": 11064, "player1_points": 49, "player2_id": 11054, "player2_points": 200, "result": "win", "winner_id": 11054}, {"id": 6540, "player1_id": 11024, "player1_points": 200, "player2_id": 11061, "player2_points": 51, "result": "win", "winner_id": 11024}, {"id": 6539, "player1_id": 11084, "player1_points": 125, "player2_id": 11047, "player2_points": 76, "result": "win", "winner_id": 11084}, {"id": 6538, "player1_id": 11026, "player1_points": 76, "player2_id": 11073, "player2_points": 51, "result": "win", "winner_id": 11026}, {"id": 6537, "player1_id": 11066, "player1_points": 106, "player2_id": 11088, "player2_points": 49, "result": "win", "winner_id": 11066}, {"id": 6536, "player1_id": 11040, "player1_points": 152, "player2_id": 11036, "player2_points": 153, "result": "win", "winner_id": 11036}, {"id": 6535, "player1_id": 11043, "player1_points": 142, "player2_id": 11068, "player2_points": 156, "result": "win", "winner_id": 11068}, {"id": 6534, "player1_id": 11074, "player1_points": 24, "player2_id": 11028, "player2_points": 155, "result": "win", "winner_id": 11028}, {"id": 6533, "player1_id": 11053, "player1_points": 74, "player2_id": 11063, "player2_points": 68, "result": "win", "winner_id": 11053}, {"id": 6532, "player1_id": 11032, "player1_points": 73, "player2_id": 11048, "player2_points": 128, "result": "win", "winner_id": 11048}, {"id": 6531, "player1_id": 11079, "player1_points": 97, "player2_id": 11050, "player2_points": 200, "result": "win", "winner_id": 11050}, {"id": 6530, "player1_id": 11090, "player1_points": 55, "player2_id": 11055, "player2_points": 141, "result": "win", "winner_id": 11055}, {"id": 6529, "player1_id": 11087, "player1_points": 175, "player2_id": 11062, "player2_points": 102, "result": "win", "winner_id": 11087}, {"id": 6528, "player1_id": 11031, "player1_points": 200, "player2_id": 11045, "player2_points": 51, "result": "win", "winner_id": 11031}, {"id": 6527, "player1_id": 11051, "player1_points": 102, "player2_id": 11094, "player2_points": 58, "result": "win", "winner_id": 11051}, {"id": 6526, "player1_id": 11072, "player1_points": 158, "player2_id": 11025, "player2_points": 121, "result": "win", "winner_id": 11072}, {"id": 6525, "player1_id": 11095, "player1_points": 39, "player2_id": 11042, "player2_points": 200, "result": "win", "winner_id": 11042}, {"id": 6524, "player1_id": 11022, "player1_points": 132, "player2_id": 11059, "player2_points": 62, "result": "win", "winner_id": 11022}, {"id": 6523, "player1_id": 11046, "player1_points": 140, "player2_id": 11093, "player2_points": 75, "result": "win", "winner_id": 11046}, {"id": 6522, "player1_id": 11057, "player1_points": 162, "player2_id": 11069, "player2_points": 22, "result": "win", "winner_id": 11057}, {"id": 6521, "player1_id": 11067, "player1_points": 200, "player2_id": 11056, "player2_points": 136, "result": "win", "winner_id": 11067}, {"id": 6520, "player1_id": 11060, "player1_points": 128, "player2_id": 11080, "player2_points": 57, "result": "win", "winner_id": 11060}, {"id": 6519, "player1_id": 11070, "player1_points": 100, "player2_id": 11049, "player2_points": 56, "result": "win", "winner_id": 11070}, {"id": 6518, "player1_id": 11071, "player1_points": 22, "player2_id": 11035, "player2_points": 200, "result": "win", "winner_id": 11035}, {"id": 6517, "player1_id": 11038, "player1_points": 118, "player2_id": 11082, "player2_points": 57, "result": "win", "winner_id": 11038}, {"id": 6516, "player1_id": 11096, "player1_points": 49, "player2_id": 11034, "player2_points": 90, "result": "win", "winner_id": 11034}, {"id": 6515, "player1_id": 11092, "player1_points": 33, "player2_id": 11037, "player2_points": 200, "result": "win", "winner_id": 11037}]}]}